mcp_weather_http/__init__.py
mcp_weather_http/__main__.py
mcp_weather_http/server.py
mcp_http_zhysfl-0.2.0.dist-info/METADATA
mcp_http_zhysfl-0.2.0.dist-info/WHEEL
mcp_http_zhysfl-0.2.0.dist-info/entry_points.txt
mcp_http_zhysfl-0.2.0.dist-info/top_level.txt
mcp_http_zhysfl-0.2.0.dist-info/RECORD
