Metadata-Version: 2.4
Name: mcp-http-zhysfl
Version: 0.2.0
Summary: 输入OpenWeather-API-KEY，获取天气信息。
Requires-Python: >=3.9
Requires-Dist: httpx>=0.28.1
Requires-Dist: mcp>=1.8.0
